docs/source/conf.py
examples/__init__.py
examples/make_lattice_fcc_ee_z.py
examples/run_tracking.py
examples/collimation/run_tracking.py
venv/bin/activate_this.py
xsuite_utils-0.1.0.data/data/examples/make_lattice_fcc_ee_z.py
xsuite_utils-0.1.0.data/data/examples/run_tracking.py
xsuite_utils-0.1.0.dist-info/licenses/LICENSE
xutil/__init__.py
xutil/common/__init__.py
xutil/common/utils.py
xutil/fcc/__init__.py
xutil/fcc/lattice_model.py
xutil/fcc/utils.py
xutil/lhc/__init__.py
xutil/lhc/utils.py
xsuite_utils-0.1.0.dist-info/METADATA
xsuite_utils-0.1.0.dist-info/WHEEL
xsuite_utils-0.1.0.dist-info/entry_points.txt
xsuite_utils-0.1.0.dist-info/top_level.txt
xsuite_utils-0.1.0.dist-info/RECORD
