Metadata-Version: 2.4
Name: xsuite-utils
Version: 0.1.0
Summary: Utilities for XSuite, focused on accelerator specific tools
Author-email: Kyriacos Skoufaris <kyriacos.skoufaris@cern.ch>, Giulia Nigrelli <giulia.nigrelli@cern.ch>, Maël Le Garrec <mael.le.garrec@cern.ch>
License: Apache-2.0
Project-URL: Homepage, https://gitlab.cern.ch/kskoufar/xutil/
Project-URL: Documentation, https://gitlab.cern.ch/kskoufar/xutil/docs
Project-URL: Repository, https://gitlab.cern.ch/kskoufar/xutil/
Project-URL: Issues, https://gitlab.cern.ch/kskoufar/xutil/issues
Classifier: Development Status :: 3 - Alpha
Classifier: Intended Audience :: Science/Research
Classifier: Topic :: Scientific/Engineering :: Physics
Classifier: Programming Language :: Python :: 3.8
Classifier: Programming Language :: Python :: 3.9
Classifier: Programming Language :: Python :: 3.10
Classifier: Operating System :: POSIX :: Linux
Classifier: Environment :: Console
Requires-Python: >=3.8
License-File: LICENSE
Requires-Dist: numpy>=1.21
Requires-Dist: cpymad>=1.9.0
Requires-Dist: xsuite>=0.27
Requires-Dist: pandas>=1.3
Requires-Dist: tfs-pandas>=2.0
Requires-Dist: matplotlib>=3.5
Requires-Dist: h5py>=3.0
Requires-Dist: tqdm>=4.0
Requires-Dist: scipy>=1.7
Requires-Dist: pylhc_submitter>=0.5
Requires-Dist: pyyaml>=6.0
Provides-Extra: test
Requires-Dist: pytest>=7.0; extra == "test"
Requires-Dist: pytest-cov>=3.0; extra == "test"
Requires-Dist: pytest-mock>=3.0; extra == "test"
Requires-Dist: pytest-xdist>=2.0; extra == "test"
Provides-Extra: doc
Requires-Dist: sphinx>=5.0; extra == "doc"
Requires-Dist: sphinx-rtd-theme>=1.0; extra == "doc"
Requires-Dist: sphinx-autoapi>=2.0; extra == "doc"
Requires-Dist: myst-parser>=0.18; extra == "doc"
Requires-Dist: nbsphinx>=0.8; extra == "doc"
Provides-Extra: dev
Requires-Dist: pre-commit>=2.0; extra == "dev"
Requires-Dist: black>=23.0; extra == "dev"
Requires-Dist: flake8>=5.0; extra == "dev"
Requires-Dist: isort>=5.0; extra == "dev"
Requires-Dist: ipython>=8.0; extra == "dev"
Dynamic: license-file
